LICENSE
MANIFEST.in
README.md
setup.py
lyrebird_bugit/__init__.py
lyrebird_bugit/apis.py
lyrebird_bugit/attachment.py
lyrebird_bugit/cache.py
lyrebird_bugit/event_handler.py
lyrebird_bugit/manifest.py
lyrebird_bugit/template_loader.py
lyrebird_bugit/upload.py
lyrebird_bugit.egg-info/PKG-INFO
lyrebird_bugit.egg-info/SOURCES.txt
lyrebird_bugit.egg-info/dependency_links.txt
lyrebird_bugit.egg-info/entry_points.txt
lyrebird_bugit.egg-info/not-zip-safe
lyrebird_bugit.egg-info/requires.txt
lyrebird_bugit.egg-info/top_level.txt
lyrebird_bugit/dist/css.worker.js
lyrebird_bugit/dist/editor.worker.js
lyrebird_bugit/dist/favicon.ico
lyrebird_bugit/dist/html.worker.js
lyrebird_bugit/dist/index.html
lyrebird_bugit/dist/json.worker.js
lyrebird_bugit/dist/ts.worker.js
lyrebird_bugit/dist/css/app.aba8aca2.css
lyrebird_bugit/dist/css/chunk-vendors.c2070dec.css
lyrebird_bugit/dist/fonts/codicon.f5ac4551.ttf
lyrebird_bugit/dist/fonts/ionicons.143146fa.woff2
lyrebird_bugit/dist/fonts/ionicons.99ac3308.woff
lyrebird_bugit/dist/fonts/ionicons.d535a25a.ttf
lyrebird_bugit/dist/img/ionicons.a2c4a261.svg
lyrebird_bugit/dist/js/app.86ccbd62.js
lyrebird_bugit/dist/js/chunk-0b65ffb6.b1e90d2b.js
lyrebird_bugit/dist/js/chunk-12950967.4794c666.js
lyrebird_bugit/dist/js/chunk-2d0a3196.525c060a.js
lyrebird_bugit/dist/js/chunk-2d0a3577.08e57b7c.js
lyrebird_bugit/dist/js/chunk-2d0a40c8.f1e3a7bf.js
lyrebird_bugit/dist/js/chunk-2d0a43df.29246f68.js
lyrebird_bugit/dist/js/chunk-2d0a4bbf.37464aac.js
lyrebird_bugit/dist/js/chunk-2d0aa90c.7dcadb75.js
lyrebird_bugit/dist/js/chunk-2d0aab07.9a68281e.js
lyrebird_bugit/dist/js/chunk-2d0abc00.7d503b65.js
lyrebird_bugit/dist/js/chunk-2d0ae937.972e1caf.js
lyrebird_bugit/dist/js/chunk-2d0aeb45.a7da3444.js
lyrebird_bugit/dist/js/chunk-2d0af08c.13b9cb9b.js
lyrebird_bugit/dist/js/chunk-2d0afa49.0d8775c1.js
lyrebird_bugit/dist/js/chunk-2d0b1fd5.28a415f7.js
lyrebird_bugit/dist/js/chunk-2d0b21d7.c86168d7.js
lyrebird_bugit/dist/js/chunk-2d0b2762.040008b6.js
lyrebird_bugit/dist/js/chunk-2d0b6187.98b8f6c5.js
lyrebird_bugit/dist/js/chunk-2d0ba136.1c2c79ef.js
lyrebird_bugit/dist/js/chunk-2d0bb267.e21a8941.js
lyrebird_bugit/dist/js/chunk-2d0bcec1.04eac3a4.js
lyrebird_bugit/dist/js/chunk-2d0bdf38.e296a2c0.js
